edu_secure_media/__init__.py
edu_secure_media/config.py
edu_secure_media/fields.py
edu_secure_media/helpers.py
edu_secure_media/urls.py
edu_secure_media/utils.py
edu_secure_media/views.py
edu_secure_media/contrib/__init__.py
edu_secure_media/contrib/drf/__init__.py
edu_secure_media/contrib/drf/urls.py
edu_secure_media/contrib/drf/views.py
edu_secure_media/handlers/__init__.py
edu_secure_media/handlers/common.py
edu_secure_media/handlers/m3.py
edu_secure_media-0.2.0.dist-info/METADATA
edu_secure_media-0.2.0.dist-info/WHEEL
edu_secure_media-0.2.0.dist-info/top_level.txt
edu_secure_media-0.2.0.dist-info/RECORD
