Metadata-Version: 2.2
Name: edu-secure-media
Version: 0.2.0
Requires-Python: >=3.9
Requires-Dist: Django
Requires-Dist: django-sendfile2
Provides-Extra: m3
Requires-Dist: m3-users; extra == "m3"
Provides-Extra: drf
Requires-Dist: djangorestframework; extra == "drf"
